LICENSE
README.md
setup.cfg
setup.py
testDKPB/__init__.py
testDKPB/example.py
testDKPB.egg-info/PKG-INFO
testDKPB.egg-info/SOURCES.txt
testDKPB.egg-info/dependency_links.txt
testDKPB.egg-info/requires.txt
testDKPB.egg-info/top_level.txt