Metadata-Version: 2.1
Name: testDKPB
Version: 0.0.1
Summary: Testing installation of Package
Home-page: https://github.com/diannekb/testDKPB
Download-URL: https://github.com/diannekb/testDKPB/archive/refs/tags/0.0.1.tar.gz
Author: Dianne Kim Bienes
Author-email: kimbienes@gmail.com
License: MIT
Keywords: pypi,tutorial
Platform: UNKNOWN
Classifier: Development Status :: 3 - Alpha
Classifier: Intended Audience :: Developers
Classifier: Topic :: Software Development :: Documentation
Classifier: License :: OSI Approved :: MIT License
Classifier: Programming Language :: Python :: 3
Classifier: Programming Language :: Python :: 3.7
Classifier: Programming Language :: Python :: 3.8
Classifier: Programming Language :: Python :: 3.9
License-File: LICENSE
